simple_jsondiff/__init__.py
simple_jsondiff/cli.py
simple_jsondiff/simple_jsondiff.py
simple_jsondiff-0.3.0.dist-info/AUTHORS.rst
simple_jsondiff-0.3.0.dist-info/LICENSE
simple_jsondiff-0.3.0.dist-info/METADATA
simple_jsondiff-0.3.0.dist-info/WHEEL
simple_jsondiff-0.3.0.dist-info/entry_points.txt
simple_jsondiff-0.3.0.dist-info/top_level.txt
simple_jsondiff-0.3.0.dist-info/RECORD
