Metadata-Version: 2.1
Name: simple-jsondiff
Version: 0.3.0
Summary: SSimple tools for diffing JSON documents.
Home-page: https://github.com/machristie/simple_jsondiff
Author: Marcus Christie
Author-email: machrist@iu.edu
License: MIT license
Keywords: simple_jsondiff
Platform: UNKNOWN
Classifier: Development Status :: 2 - Pre-Alpha
Classifier: Intended Audience :: Developers
Classifier: License :: OSI Approved :: MIT License
Classifier: Natural Language :: English
Classifier: Programming Language :: Python :: 2
Classifier: Programming Language :: Python :: 2.7
Classifier: Programming Language :: Python :: 3
Classifier: Programming Language :: Python :: 3.4
Classifier: Programming Language :: Python :: 3.5
Classifier: Programming Language :: Python :: 3.6
Classifier: Programming Language :: Python :: 3.7
Requires-Dist: Click (>=6.0)
